{
    "view": {},
    "props": {
        "labelColor": {
            "type": "color",
            "default": "text.default.secondary"
        },
        "titleColor": {
            "type": "color",
            "default": "text.default.primary"
        },
        "subtitleColor": {
            "type": "color",
            "default": "text.default.secondary"
        },
        "disclosureIconColor": {
            "type": "color",
            "default": "text.default.secondary"
        },
        "backgroundColor": {
            "type": "color",
            "default": "surface.default.clear",
            "states": [
                {
                    "state": [
                        "hovered"
                    ],
                    "value": "surface.default.transparent-secondary"
                }
            ]
        },
        "disableAlpha": {
            "type": "float",
            "value": 0.4
        },
        "shape": {
            "type": "shape",
            "value": "round.xxs"
        },
        "height": {
            "type": "dimension",
            "value": 52.0
        },
        "contentPaddingStart": {
            "type": "dimension",
            "value": 12.0
        },
        "contentPaddingEnd": {
            "type": "dimension",
            "value": 12.0
        },
        "titleStyle": {
            "type": "typography",
            "value": "body.l.normal"
        },
        "labelStyle": {
            "type": "typography",
            "value": "body.xs.medium"
        },
        "subtitleStyle": {
            "type": "typography",
            "value": "body.m.normal"
        },
        "disclosureIcon": {
            "type": "icon",
            "value": "disclosure.right.outline.24"
        },
        "paddingStart": {
            "type": "dimension",
            "value": 16
        },
        "paddingEnd": {
            "type": "dimension",
            "value": 16
        },
        "paddingTop": {
            "type": "dimension",
            "value": 12
        },
        "paddingBottom": {
            "type": "dimension",
            "value": 12
        }
    },
    "variations": []
}