{
    "variations": {
        "color": {
            "default": {
                "contentColor": {
                    "default": "text.inverse.primary",
                    "states": [
                        {
                            "focused": false,
                            "pressed": true,
                            "hovered": false,
                            "value": "text.inverse.primary-active"
                        },
                        {
                            "focused": false,
                            "pressed": false,
                            "hovered": true,
                            "value": "text.inverse.primary-hover"
                        }
                    ]
                }, 
                "backgroundColor": {
                    "default": "surface.default.solid-default",
                    "states": [
                        {
                            "focused": false,
                            "pressed": true,
                            "hovered": false,
                            "value": "surface.default.solid-default-active"
                        },
                        {
                            "focused": false,
                            "pressed": false,
                            "hovered": true,
                            "value": "surface.default.solid-default-hover"
                        }
                    ]
                }, 
                "valueColor": {
                    "default": "text.inverse.secondary",
                    "states": [
                        {
                            "focused": false,
                            "pressed": true,
                            "hovered": false,
                            "value": "text.inverse.secondary-active"
                        },
                        {
                            "focused": false,
                            "pressed": false,
                            "hovered": true,
                            "value": "text.inverse.secondary-hover"
                        }
                    ]
                }
            },
            "secondary": {
                "contentColor": {
                    "default": "text.default.primary",
                    "states": [
                        {
                            "focused": false,
                            "pressed": true,
                            "hovered": false,
                            "value": "text.default.primary-active"
                        },
                        {
                            "focused": false,
                            "pressed": false,
                            "hovered": true,
                            "value": "text.default.primary-hover"
                        }
                    ]
                }, 
                "backgroundColor": {
                    "default": "surface.default.transparent-secondary",
                    "states": [
                        {
                            "focused": false,
                            "pressed": true,
                            "hovered": false,
                            "value": "surface.default.transparent-secondary-active"
                        },
                        {
                            "focused": false,
                            "pressed": false,
                            "hovered": true,
                            "value": "surface.default.transparent-secondary-hover"
                        }
                    ]
                }, 
                "valueColor": {
                    "default": "text.default.secondary",
                    "states": [
                        {
                            "focused": false,
                            "pressed": true,
                            "hovered": false,
                            "value": "text.default.secondary-active"
                        },
                        {
                            "focused": false,
                            "pressed": false,
                            "hovered": true,
                            "value": "text.default.secondary-hover"
                        }
                    ]
                }
            },
            "accent": {
                "contentColor": {
                    "default": "text.on-dark.primary",
                    "states": [
                        {
                            "focused": false,
                            "pressed": true,
                            "hovered": false,
                            "value": "text.on-dark.primary-active"
                        },
                        {
                            "focused": false,
                            "pressed": false,
                            "hovered": true,
                            "value": "text.on-dark.primary-hover"
                        }
                    ]
                }, 
                "backgroundColor": {
                    "default": "surface.default.accent",
                    "states": [
                        {
                            "focused": false,
                            "pressed": true,
                            "hovered": false,
                            "value": "surface.default.accent-active"
                        },
                        {
                            "focused": false,
                            "pressed": false,
                            "hovered": true,
                            "value": "surface.default.accent-hover"
                        }
                    ]
                }, 
                "valueColor": {
                    "default": "text.on-dark.secondary",
                    "states": [
                        {
                            "focused": false,
                            "pressed": true,
                            "hovered": false,
                            "value": "text.on-dark.secondary-active"
                        },
                        {
                            "focused": false,
                            "pressed": false,
                            "hovered": true,
                            "value": "text.on-dark.secondary-hover"
                        }
                    ]
                }
            },
            "positive": {
                "contentColor": {
                    "default": "text.on-dark.primary",
                    "states": [
                        {
                            "focused": false,
                            "pressed": true,
                            "hovered": false,
                            "value": "text.on-dark.primary-active"
                        },
                        {
                            "focused": false,
                            "pressed": false,
                            "hovered": true,
                            "value": "text.on-dark.primary-hover"
                        }
                    ]
                }, 
                "backgroundColor": {
                    "default": "surface.default.positive",
                    "states": [
                        {
                            "focused": false,
                            "pressed": true,
                            "hovered": false,
                            "value": "surface.default.positive-active"
                        },
                        {
                            "focused": false,
                            "pressed": false,
                            "hovered": true,
                            "value": "surface.default.positive-hover"
                        }
                    ]
                }, 
                "valueColor": {
                    "default": "text.on-dark.secondary",
                    "states": [
                        {
                            "focused": false,
                            "pressed": true,
                            "hovered": false,
                            "value": "text.on-dark.secondary-active"
                        },
                        {
                            "focused": false,
                            "pressed": false,
                            "hovered": true,
                            "value": "text.on-dark.secondary-hover"
                        }
                    ]
                }
            },
            "negative": {
                "contentColor": {
                    "default": "text.on-dark.primary",
                    "states": [
                        {
                            "focused": false,
                            "pressed": true,
                            "hovered": false,
                            "value": "text.on-dark.primary-active"
                        },
                        {
                            "focused": false,
                            "pressed": false,
                            "hovered": true,
                            "value": "text.on-dark.primary-hover"
                        }
                    ]
                }, 
                "backgroundColor": {
                    "default": "surface.default.negative",
                    "states": [
                        {
                            "focused": false,
                            "pressed": true,
                            "hovered": false,
                            "value": "surface.default.negative-active"
                        },
                        {
                            "focused": false,
                            "pressed": false,
                            "hovered": true,
                            "value": "surface.default.negative-hover"
                        }
                    ]
                },
                "valueColor": {
                   "default": "text.on-dark.secondary",
                    "states": [
                        {
                            "focused": false,
                            "pressed": true,
                            "hovered": false,
                            "value": "text.on-dark.secondary-active"
                        },
                        {
                            "focused": false,
                            "pressed": false,
                            "hovered": true,
                            "value": "text.on-dark.secondary-hover"
                        }
                    ]
                }
            },
            "warning": {
                "contentColor": {
                    "default": "text.on-dark.primary",
                    "states": [
                        {
                            "focused": false,
                            "pressed": true,
                            "hovered": false,
                            "value": "text.on-dark.primary-active"
                        },
                        {
                            "focused": false,
                            "pressed": false,
                            "hovered": true,
                            "value": "text.on-dark.primary-hover"
                        }
                    ]
                }, 
                "backgroundColor": {
                    "default": "surface.default.warning",
                    "states": [
                        {
                            "focused": false,
                            "pressed": true,
                            "hovered": false,
                            "value": "surface.default.warning-active"
                        },
                        {
                            "focused": false,
                            "pressed": false,
                            "hovered": true,
                            "value": "surface.default.warning-hover"
                        }
                    ]
                }, 
                "valueColor": {
                    "default": "text.on-dark.secondary",
                    "states": [
                        {
                            "focused": false,
                            "pressed": true,
                            "hovered": false,
                            "value": "text.on-dark.secondary-active"
                        },
                        {
                            "focused": false,
                            "pressed": false,
                            "hovered": true,
                            "value": "text.on-dark.secondary-hover"
                        }
                    ]
                }
            },
            "clear": {
                "contentColor": {
                    "default": "text.default.primary",
                    "states": [
                        {
                            "focused": false,
                            "pressed": true,
                            "hovered": false,
                            "value": "text.default.primary-active"
                        },
                        {
                            "focused": false,
                            "pressed": false,
                            "hovered": true,
                            "value": "text.default.primary-hover"
                        }
                    ]
                }, 
                "backgroundColor": {
                    "default": "surface.default.clear",
                    "states": [
                        {
                            "focused": false,
                            "pressed": true,
                            "hovered": false,
                            "value": "surface.default.clear-active"
                        },
                        {
                            "focused": false,
                            "pressed": false,
                            "hovered": true,
                            "value": "surface.default.clear-hover"
                        }
                    ]
                }, 
                "valueColor": {
                    "default": "text.default.secondary",
                    "states": [
                        {
                            "focused": false,
                            "pressed": true,
                            "hovered": false,
                            "value": "text.default.secondary-active"
                        },
                        {
                            "focused": false,
                            "pressed": false,
                            "hovered": true,
                            "value": "text.default.secondary-hover"
                        }
                    ]
                }
            },
            "dark": {
                "contentColor": {
                    "default": "text.on-dark.primary",
                    "states": [
                        {
                            "focused": false,
                            "pressed": true,
                            "hovered": false,
                            "value": "text.on-dark.primary-active"
                        },
                        {
                            "focused": false,
                            "pressed": false,
                            "hovered": true,
                            "value": "text.on-dark.primary-hover"
                        }
                    ]
                }, 
                "backgroundColor": {
                    "default": "surface.on-light.transparent-deep",
                    "states": [
                        {
                            "focused": false,
                            "pressed": true,
                            "hovered": false,
                            "value": "surface.on-light.transparent-deep-active"
                        },
                        {
                            "focused": false,
                            "pressed": false,
                            "hovered": true,
                            "value": "surface.on-light.transparent-deep-hover"
                        }
                    ]
                }, 
                "valueColor": {
                    "default": "text.on-dark.secondary",
                    "states": [
                        {
                            "focused": false,
                            "pressed": true,
                            "hovered": false,
                            "value": "text.on-dark.secondary-active"
                        },
                        {
                            "focused": false,
                            "pressed": false,
                            "hovered": true,
                            "value": "text.on-dark.secondary-hover"
                        }
                    ]
                }
            },
            "black": {
                "contentColor": {
                    "default": "text.on-dark.primary",
                    "states": [
                        {
                            "focused": false,
                            "pressed": true,
                            "hovered": false,
                            "value": "text.on-dark.primary-active"
                        },
                        {
                            "focused": false,
                            "pressed": false,
                            "hovered": true,
                            "value": "text.on-dark.primary-hover"
                        }
                    ]
                }, 
                "backgroundColor": {
                    "default": "tsurface.on-light.solid-default",
                    "states": [
                        {
                            "focused": false,
                            "pressed": true,
                            "hovered": false,
                            "value": "surface.on-light.solid-default-active"
                        },
                        {
                            "focused": false,
                            "pressed": false,
                            "hovered": true,
                            "value": "surface.on-light.solid-default-hover"
                        }
                    ]
                }, 
                "valueColor": {
                    "default": "text.on-dark.secondary",
                    "states": [
                        {
                            "focused": false,
                            "pressed": true,
                            "hovered": false,
                            "value": "text.on-dark.secondary-active"
                        },
                        {
                            "focused": false,
                            "pressed": false,
                            "hovered": true,
                            "value": "text.on-dark.secondary-hover"
                        }
                    ]
                }
            },
            "white": {
                "contentColor": {
                    "default": "text.on-light.primary",
                    "states": [
                        {
                            "focused": false,
                            "pressed": true,
                            "hovered": false,
                            "value": "text.on-light.primary-active"
                        },
                        {
                            "focused": false,
                            "pressed": false,
                            "hovered": true,
                            "value": "text.on-light.primary-hover"
                        }
                    ]
                }, 
                "backgroundColor": {
                    "default": "surface.on-light.solid-default",
                    "states": [
                        {
                            "focused": false,
                            "pressed": true,
                            "hovered": false,
                            "value": "surface.on-light.solid-default-active"
                        },
                        {
                            "focused": false,
                            "pressed": false,
                            "hovered": true,
                            "value": "surface.on-light.solid-default-hover"
                        }
                    ]
                }, 
                "valueColor": {
                    "default": "text.on-light.secondary",
                    "states": [
                        {
                            "focused": false,
                            "pressed": true,
                            "hovered": false,
                            "value": "text.on-light.secondary-active"
                        },
                        {
                            "focused": false,
                            "pressed": false,
                            "hovered": true,
                            "value": "text.on-light.secondary-hover"
                        }
                    ]
                }
            }
        },
        "size": {
            "l": {
                "shape": "round.l",
                "height": 56, 
                "paddingStart": 16,
                "paddingEnd": 16,
                "minWidth": 56,
                "iconSize": 24,
                "spinnerSize": 22
            },
            "m": {
                "shape": "round.m",
                "height": 48,
                "paddingStart": 12,
                "paddingEnd": 12,
                "minWidth": 48,
                "iconSize": 24,
                "spinnerSize": 22
            },
            "s": {
                "shape": "round.s",
                "height": 40,
                "paddingStart": 8,
                "paddingEnd": 8,
                "minWidth": 40,
                "iconSize": 24,
                "spinnerSize": 22
            },
            "xs": {
                "shape": "round.xs",
                "height": 32,
                "paddingStart": 8,
                "paddingEnd": 8,
                "minWidth": 32,
                "iconSize": 16,
                "spinnerSize": 16
            }
        }
    }
}